{
   "data":[
      {
         "id":4411990,
         "sd":"2017-04-15T18:00:00.000+0400",
         "h":"Everton FC",
         "a":"Burnley FC",
         "odds":{
            "bothToScore":[
               {
                  "id":539904063,
                  "name":"yes",
                  "value":2.1
               },
               {
                  "id":539904151,
                  "name":"no",
                  "value":1.75
               }
            ],
            "doubleChance":[
               {
                  "id":537042254,
                  "name":"1x",
                  "value":1.1
               },
               {
                  "id":537042255,
                  "name":"12",
                  "value":1.22
               },
               {
                  "id":537042256,
                  "name":"x2",
                  "value":2.88
               }
            ],
            "drawNoBet":[
               {
                  "id":537042251,
                  "name":"2",
                  "value":6.06
               },
               {
                  "id":537042257,
                  "name":"1",
                  "value":1.13
               }
            ],
            "totalGoals":[
               {
                  "id":539904091,
                  "name":"over",
                  "sbv":"2.5",
                  "value":1.85
               },
               {
                  "id":539904635,
                  "name":"under",
                  "sbv":"2.5",
                  "value":1.95
               }
            ]
         }
      },
      {
         "id":4411997,
         "sd":"2017-04-15T18:00:00.000+0400",
         "h":"Crystal Palace",
         "a":"Leicester City",
         "odds":{
            "bothToScore":[
               {
                  "id":539902001,
                  "name":"yes",
                  "value":1.9
               },
               {
                  "id":539902336,
                  "name":"no",
                  "value":1.9
               }
            ],
            "doubleChance":[
               {
                  "id":537042259,
                  "name":"12",
                  "value":1.33
               },
               {
                  "id":537042264,
                  "name":"x2",
                  "value":1.93
               },
               {
                  "id":537042265,
                  "name":"1x",
                  "value":1.26
               }
            ],
            "drawNoBet":[
               {
                  "id":537042261,
                  "name":"2",
                  "value":3.03
               },
               {
                  "id":537042263,
                  "name":"1",
                  "value":1.4
               }
            ],
            "3way":[
               {
                  "id":537042258,
                  "name":"x",
                  "value":3.6
               },
               {
                  "id":537042260,
                  "name":"2",
                  "value":4.2
               },
               {
                  "id":537042262,
                  "name":"1",
                  "value":1.95
               }
            ],
            "totalGoals":[
               {
                  "id":539902029,
                  "name":"over",
                  "sbv":"2.5",
                  "value":2.05
               },
               {
                  "id":539903923,
                  "name":"under",
                  "sbv":"2.5",
                  "value":1.8
               }
            ]
         }
      },
      {
         "id":4411999,
         "sd":"2017-04-16T16:30:00.000+0400",
         "h":"West Bromwich Albion",
         "a":"Liverpool FC",
         "odds":{
            "bothToScore":[
               {
                  "id":539904539,
                  "name":"yes",
                  "value":1.85
               },
               {
                  "id":539904678,
                  "name":"no",
                  "value":1.95
               }
            ],
            "drawNoBet":[
               {
                  "id":537056429,
                  "name":"1",
                  "value":3.24
               },
               {
                  "id":537056430,
                  "name":"2",
                  "value":1.35
               }
            ],
            "3way":[
               {
                  "id":537056426,
                  "name":"x",
                  "value":3.7
               },
               {
                  "id":537056432,
                  "name":"2",
                  "value":1.85
               },
               {
                  "id":537056433,
                  "name":"1",
                  "value":4.45
               }
            ],
            "totalGoals":[
               {
                  "id":539904266,
                  "name":"under",
                  "value":1.85
               },
               {
                  "id":539905431,
                  "name":"over",
                  "sbv":"2.5",
                  "value":1.95
               }
            ]
         }
      },
      {
         "id":4412013,
         "sd":"2017-04-22T18:00:00.000+0400",
         "h":"Swansea City",
         "a":"Stoke City",
         "odds":{
            "bothToScore":[
               {
                  "id":544479682,
                  "name":"yes",
                  "value":1.85
               },
               {
                  "id":544479827,
                  "name":"no",
                  "value":2.0
               }
            ],
            "doubleChance":[
               {
                  "id":541151604,
                  "name":"x2",
                  "value":1.67
               },
               {
                  "id":541151606,
                  "name":"1x",
                  "value":1.37
               },
               {
                  "id":541151607,
                  "name":"12",
                  "value":1.35
               }
            ],
            "drawNoBet":[
               {
                  "id":541151601,
                  "name":"1",
                  "value":1.62
               },
               {
                  "id":541151602,
                  "name":"2",
                  "value":2.32
               }
            ],
            "3way":[
               {
                  "id":541151600,
                  "name":"1",
                  "value":2.3
               },
               {
                  "id":541151603,
                  "name":"x",
                  "value":3.4
               },
               {
                  "id":541151605,
                  "name":"2",
                  "value":3.3
               }
            ],
            "totalGoals":[
               {
                  "id":544476634,
                  "name":"under",
                  "sbv":"2.5",
                  "value":1.8
               },
               {
                  "id":544476635,
                  "name":"over",
                  "sbv":"2.5",
                  "value":2.05
               }
            ]
         }
      },
      {
         "id":4412022,
         "sd":"2017-04-22T18:00:00.000+0400",
         "h":"Hull City",
         "a":"Watford FC",
         "odds":{
            "bothToScore":[
               {
                  "id":544478626,
                  "name":"yes",
                  "value":1.85
               },
               {
                  "id":544480361,
                  "name":"no",
                  "value":2.0
               }
            ],
            "doubleChance":[
               {
                  "id":541151193,
                  "name":"1x",
                  "value":1.31
               },
               {
                  "id":541151197,
                  "name":"12",
                  "value":1.35
               },
               {
                  "id":541151198,
                  "name":"x2",
                  "value":1.82
               }
            ],
            "drawNoBet":[
               {
                  "id":541151191,
                  "name":"1",
                  "value":1.5
               },
               {
                  "id":541151194,
                  "name":"2",
                  "value":2.71
               }
            ],
            "3way":[
               {
                  "id":541151192,
                  "name":"1",
                  "value":2.1
               },
               {
                  "id":541151195,
                  "name":"x",
                  "value":3.5
               },
               {
                  "id":541151196,
                  "name":"2",
                  "value":3.8
               }
            ],
            "totalGoals":[
               {
                  "id":544476632,
                  "name":"under",
                  "sbv":"2.5",
                  "value":1.8
               },
               {
                  "id":544476633,
                  "name":"over",
                  "sbv":"2.5",
                  "value":2.0
               }
            ]
         }
      },
      {
         "id":4412024,
         "sd":"2017-04-15T15:30:00.000+0400",
         "h":"Tottenham Hotspur",
         "a":"Bournemouth AFC",
         "odds":{
            "bothToScore":[
               {
                  "id":539906245,
                  "name":"yes",
                  "value":1.9
               },
               {
                  "id":539907204,
                  "name":"no",
                  "value":1.9
               }
            ],
            "doubleChance":[
               {
                  "id":537042243,
                  "name":"12",
                  "value":1.15
               },
               {
                  "id":537042245,
                  "name":"1x",
                  "value":1.07
               },
               {
                  "id":537042248,
                  "name":"x2",
                  "value":3.95
               }
            ],
            "drawNoBet":[
               {
                  "id":537042242,
                  "name":"2",
                  "value":9.03
               },
               {
                  "id":537042249,
                  "name":"1",
                  "value":1.09
               }
            ],
            "3way":[
               {
                  "id":537042244,
                  "name":"1",
                  "value":1.3
               },
               {
                  "id":537042246,
                  "name":"x",
                  "value":6.25
               },
               {
                  "id":537042247,
                  "name":"2",
                  "value":10.75
               }
            ],
            "totalGoals":[
               {
                  "id":539901568,
                  "name":"over",
                  "sbv":"2.5",
                  "value":1.45
               },
               {
                  "id":539901570,
                  "name":"under",
                  "sbv":"2.5",
                  "value":2.7
               }
            ]
         }
      },
      {
         "id":4412026,
         "sd":"2017-04-17T23:00:00.000+0400",
         "h":"Middlesbrough FC",
         "a":"Arsenal FC",
         "odds":{
            "bothToScore":[
               {
                  "id":539903940,
                  "name":"yes",
                  "value":1.85
               },
               {
                  "id":539904262,
                  "name":"no",
                  "value":2.0
               }
            ],
            "doubleChance":[
               {
                  "id":537056450,
                  "name":"x2",
                  "value":1.15
               },
               {
                  "id":537056451,
                  "name":"12",
                  "value":1.25
               },
               {
                  "id":537056457,
                  "name":"1x",
                  "value":2.65
               }
            ],
            "drawNoBet":[
               {
                  "id":537056452,
                  "name":"1",
                  "value":5.05
               },
               {
                  "id":537056455,
                  "name":"2",
                  "value":1.2
               }
            ],
            "3way":[
               {
                  "id":537056453,
                  "name":"x",
                  "value":4.5
               },
               {
                  "id":537056454,
                  "name":"2",
                  "value":1.55
               },
               {
                  "id":537056456,
                  "name":"1",
                  "value":6.5
               }
            ],
            "totalGoals":[
               {
                  "id":539904878,
                  "name":"over",
                  "sbv":"2.5",
                  "value":1.7
               },
               {
                  "id":539905362,
                  "name":"under",
                  "sbv":"2.5",
                  "value":2.15
               }
            ]
         }
      },
      {
         "id":4412035,
         "sd":"2017-04-16T19:00:00.000+0400",
         "h":"Manchester United",
         "a":"Chelsea FC",
         "odds":{
            "bothToScore":[
               {
                  "id":539902735,
                  "name":"no",
                  "value":1.85
               },
               {
                  "id":539904072,
                  "name":"yes",
                  "value":1.95
               }
            ],
            "doubleChance":[
               {
                  "id":537056420,
                  "name":"12",
                  "value":1.38
               },
               {
                  "id":537056421,
                  "name":"x2",
                  "value":1.52
               },
               {
                  "id":537056424,
                  "name":"1x",
                  "value":1.44
               }
            ],
            "drawNoBet":[
               {
                  "id":537056418,
                  "name":"1",
                  "value":1.82
               },
               {
                  "id":537056425,
                  "name":"2",
                  "value":1.99
               }
            ],
            "3way":[
               {
                  "id":537056419,
                  "name":"x",
                  "value":3.2
               },
               {
                  "id":537056422,
                  "name":"2",
                  "value":2.9
               },
               {
                  "id":537056423,
                  "name":"1",
                  "value":2.65
               }
            ],
            "totalGoals":[
               {
                  "id":539903217,
                  "name":"under",
                  "sbv":"2.5",
                  "value":1.65
               },
               {
                  "id":539905194,
                  "name":"over",
                  "sbv":"2.5",
                  "value":2.25
               }
            ]
         }
      },
      {
         "id":4412038,
         "sd":"2017-04-15T20:30:00.000+0400",
         "h":"Southampton FC",
         "a":"Manchester City",
         "odds":{
            "bothToScore":[
               {
                  "id":539904615,
                  "name":"yes",
                  "value":1.7
               },
               {
                  "id":539905720,
                  "name":"no",
                  "value":2.2
               }
            ],
            "doubleChance":[
               {
                  "id":537056382,
                  "name":"1x",
                  "value":2.15
               },
               {
                  "id":537056383,
                  "name":"x2",
                  "value":1.22
               },
               {
                  "id":537056386,
                  "name":"12",
                  "value":1.26
               }
            ],
            "3way":[
               {
                  "id":537056385,
                  "name":"x",
                  "value":4.05
               },
               {
                  "id":537056387,
                  "name":"2",
                  "value":1.75
               },
               {
                  "id":537056389,
                  "name":"1",
                  "value":4.6
               }
            ],
            "totalGoals":[
               {
                  "id":539903172,
                  "name":"under",
                  "sbv":"2.5",
                  "value":2.2
               },
               {
                  "id":539905710,
                  "name":"over",
                  "sbv":"2.5",
                  "value":1.7
               }
            ]
         }
      },
      {
         "id":4412042,
         "sd":"2017-04-15T18:00:00.000+0400",
         "h":"Stoke City",
         "a":"Hull City",
         "odds":{
            "bothToScore":[
               {
                  "id":539906375,
                  "name":"yes",
                  "value":1.95
               },
               {
                  "id":539907099,
                  "name":"no",
                  "value":1.85
               }
            ],
            "doubleChance":[
               {
                  "id":537056400,
                  "name":"1x",
                  "value":1.26
               },
               {
                  "id":537056404,
                  "name":"x2",
                  "value":1.88
               },
               {
                  "id":537056405,
                  "name":"12",
                  "value":1.34
               }
            ],
            "drawNoBet":[
               {
                  "id":537056403,
                  "name":"2",
                  "value":2.94
               },
               {
                  "id":537056406,
                  "name":"1",
                  "value":1.42
               }
            ],
            "3way":[
               {
                  "id":537056401,
                  "name":"x",
                  "value":3.45
               },
               {
                  "id":537056402,
                  "name":"2",
                  "value":4.15
               },
               {
                  "id":537056407,
                  "name":"1",
                  "value":2.0
               }
            ],
            "totalGoals":[
               {
                  "id":539901515,
                  "name":"under",
                  "sbv":"2.5",
                  "value":1.7
               },
               {
                  "id":539901516,
                  "name":"over",
                  "sbv":"2.5",
                  "value":2.15
               }
            ]
         }
      },
      {
         "id":4412044,
         "sd":"2017-04-23T19:30:00.000+0400",
         "h":"Liverpool FC",
         "a":"Crystal Palace",
         "odds":{
            "bothToScore":[
               {
                  "id":544477740,
                  "name":"no",
                  "value":2.05
               },
               {
                  "id":544478014,
                  "name":"yes",
                  "value":1.8
               }
            ],
            "doubleChance":[
               {
                  "id":541151616,
                  "name":"1x",
                  "value":1.14
               },
               {
                  "id":541151617,
                  "name":"12",
                  "value":1.23
               },
               {
                  "id":541151623,
                  "name":"x2",
                  "value":2.55
               }
            ],
            "drawNoBet":[
               {
                  "id":541151620,
                  "name":"2",
                  "value":4.65
               },
               {
                  "id":541151622,
                  "name":"1",
                  "value":1.2
               }
            ],
            "3way":[
               {
                  "id":541151618,
                  "name":"1",
                  "value":1.55
               },
               {
                  "id":541151619,
                  "name":"2",
                  "value":6.0
               },
               {
                  "id":541151621,
                  "name":"x",
                  "value":4.45
               }
            ],
            "totalGoals":[
               {
                  "id":544476638,
                  "name":"over",
                  "sbv":"2.5",
                  "value":1.7
               },
               {
                  "id":544476639,
                  "name":"under",
                  "sbv":"2.5",
                  "value":2.2
               }
            ]
         }
      },
      {
         "id":4412047,
         "sd":"2017-04-15T18:00:00.000+0400",
         "h":"Sunderland AFC",
         "a":"West Ham Utd",
         "odds":{
            "bothToScore":[
               {
                  "id":539901763,
                  "name":"yes",
                  "value":1.7
               },
               {
                  "id":539902876,
                  "name":"no",
                  "value":2.2
               }
            ],
            "doubleChance":[
               {
                  "id":537056394,
                  "name":"1x",
                  "value":1.68
               },
               {
                  "id":537056398,
                  "name":"12",
                  "value":1.34
               },
               {
                  "id":537056399,
                  "name":"x2",
                  "value":1.38
               }
            ],
            "drawNoBet":[
               {
                  "id":537056392,
                  "name":"1",
                  "value":2.32
               },
               {
                  "id":537056397,
                  "name":"2",
                  "value":1.64
               }
            ],
            "3way":[
               {
                  "id":537056393,
                  "name":"x",
                  "value":3.5
               },
               {
                  "id":537056395,
                  "name":"1",
                  "value":3.25
               },
               {
                  "id":537056396,
                  "name":"2",
                  "value":2.3
               }
            ],
            "totalGoals":[
               {
                  "id":539901917,
                  "name":"over",
                  "sbv":"2.5",
                  "value":1.85
               },
               {
                  "id":539901937,
                  "name":"under",
                  "sbv":"2.5",
                  "value":2.0
               }
            ]
         }
      },
      {
         "id":4412051,
         "sd":"2017-04-15T18:00:00.000+0400",
         "h":"Watford FC",
         "a":"Swansea City",
         "odds":{
            "bothToScore":[
               {
                  "id":539906985,
                  "name":"no",
                  "value":2.0
               },
               {
                  "id":539907188,
                  "name":"yes",
                  "value":1.8
               }
            ],
            "doubleChance":[
               {
                  "id":537056438,
                  "name":"1x",
                  "value":1.43
               },
               {
                  "id":537056440,
                  "name":"x2",
                  "value":1.58
               },
               {
                  "id":537056442,
                  "name":"12",
                  "value":1.36
               }
            ],
            "drawNoBet":[
               {
                  "id":537056441,
                  "name":"2",
                  "value":2.1
               },
               {
                  "id":537056443,
                  "name":"1",
                  "value":1.75
               }
            ],
            "3way":[
               {
                  "id":537056439,
                  "name":"1",
                  "value":2.5
               },
               {
                  "id":537056444,
                  "name":"x",
                  "value":3.35
               },
               {
                  "id":537056445,
                  "name":"2",
                  "value":3.0
               }
            ],
            "totalGoals":[
               {
                  "id":539901898,
                  "name":"under",
                  "sbv":"2.5",
                  "value":1.75
               },
               {
                  "id":539901902,
                  "name":"over",
                  "sbv":"2.5",
                  "value":2.05
               }
            ]
         }
      },
      {
         "id":4412076,
         "sd":"2017-04-22T18:00:00.000+0400",
         "h":"West Ham Utd",
         "a":"Everton FC",
         "odds":{
            "bothToScore":[
               {
                  "id":544478850,
                  "name":"yes",
                  "value":1.6
               },
               {
                  "id":544480422,
                  "name":"no",
                  "value":2.3
               }
            ],
            "doubleChance":[
               {
                  "id":541151624,
                  "name":"x2",
                  "value":1.42
               },
               {
                  "id":541151626,
                  "name":"12",
                  "value":1.34
               },
               {
                  "id":541151630,
                  "name":"1x",
                  "value":1.62
               }
            ],
            "drawNoBet":[
               {
                  "id":541151625,
                  "name":"1",
                  "value":2.17
               },
               {
                  "id":541151627,
                  "name":"2",
                  "value":1.71
               }
            ],
            "3way":[
               {
                  "id":541151628,
                  "name":"1",
                  "value":3.05
               },
               {
                  "id":541151629,
                  "name":"2",
                  "value":2.4
               },
               {
                  "id":541151631,
                  "name":"x",
                  "value":3.5
               }
            ],
            "totalGoals":[
               {
                  "id":544476636,
                  "name":"under",
                  "sbv":"2.5",
                  "value":2.1
               },
               {
                  "id":544476637,
                  "name":"over",
                  "sbv":"2.5",
                  "value":1.75
               }
            ]
         }
      },
      {
         "id":4412089,
         "sd":"2017-04-22T18:00:00.000+0400",
         "h":"Bournemouth AFC",
         "a":"Middlesbrough FC",
         "odds":{
            "bothToScore":[
               {
                  "id":544477696,
                  "name":"no",
                  "value":1.9
               },
               {
                  "id":544479206,
                  "name":"yes",
                  "value":1.9
               }
            ],
            "doubleChance":[
               {
                  "id":541151181,
                  "name":"1x",
                  "value":1.22
               },
               {
                  "id":541151184,
                  "name":"12",
                  "value":1.33
               },
               {
                  "id":541151188,
                  "name":"x2",
                  "value":2.06
               }
            ],
            "drawNoBet":[
               {
                  "id":541151183,
                  "name":"1",
                  "value":1.34
               },
               {
                  "id":541151186,
                  "name":"2",
                  "value":3.44
               }
            ],
            "3way":[
               {
                  "id":541151182,
                  "name":"2",
                  "value":4.75
               },
               {
                  "id":541151185,
                  "name":"x",
                  "value":3.65
               },
               {
                  "id":541151187,
                  "name":"1",
                  "value":1.85
               }
            ],
            "totalGoals":[
               {
                  "id":544476626,
                  "name":"over",
                  "sbv":"2.5",
                  "value":2.0
               },
               {
                  "id":544476627,
                  "name":"under",
                  "sbv":"2.5",
                  "value":1.8
               }
            ]
         }
      },
      {
         "id":4412099,
         "sd":"2017-04-23T17:15:00.000+0400",
         "h":"Burnley FC",
         "a":"Manchester United",
         "odds":{
            "bothToScore":[
               {
                  "id":544479049,
                  "name":"yes",
                  "value":2.3
               },
               {
                  "id":544479780,
                  "name":"no",
                  "value":1.6
               }
            ],
            "doubleChance":[
               {
                  "id":541151609,
                  "name":"12",
                  "value":1.26
               },
               {
                  "id":541151612,
                  "name":"1x",
                  "value":2.6
               },
               {
                  "id":541151615,
                  "name":"x2",
                  "value":1.12
               }
            ],
            "drawNoBet":[
               {
                  "id":541151610,
                  "name":"1",
                  "value":5.31
               },
               {
                  "id":541151613,
                  "name":"2",
                  "value":1.17
               }
            ],
            "3way":[
               {
                  "id":541151608,
                  "name":"2",
                  "value":1.55
               },
               {
                  "id":541151611,
                  "name":"x",
                  "value":4.15
               },
               {
                  "id":541151614,
                  "name":"1",
                  "value":7.0
               }
            ],
            "totalGoals":[
               {
                  "id":544476630,
                  "name":"under",
                  "sbv":"2.5",
                  "value":1.7
               },
               {
                  "id":544476631,
                  "name":"over",
                  "sbv":"2.5",
                  "value":2.15
               }
            ]
         }
      }
   ]
}